paperscrollsdk/__init__.py
paperscrollsdk/client.py
paperscrollsdk/exceptions.py
paperscrollsdk/methods.py
paperscrollsdk-1.0.0.dist-info/METADATA
paperscrollsdk-1.0.0.dist-info/WHEEL
paperscrollsdk-1.0.0.dist-info/top_level.txt
paperscrollsdk-1.0.0.dist-info/RECORD
