Metadata-Version: 2.1
Name: paperscrollsdk
Version: 1.0.0
Summary: A simple wrapper for VK game PaperScroll!
Home-page: https://github.com/KotRikD/paper-scroll-sdk-py
Author: KotRik
Author-email: supadmin@kotrik.ru
License: UNKNOWN
Platform: UNKNOWN
Classifier: Programming Language :: Python :: 3
Classifier: License :: OSI Approved :: MIT License
Classifier: Operating System :: OS Independent
